[
    {
        "id": "emp_6996d739d2d8e",
        "image": "uploads\/emp_6996d739d26f8.jpg",
        "name": "John Doe",
        "position": "web developer",
        "description": "",
        "email": "johndoe@gmail.com",
        "linkedin": "https:\/\/www.linkedin.com\/feed\/"
    },
    {
        "id": "emp_6997f04444a21",
        "image": "uploads\/emp_6997f04444458.png",
        "name": "Johnson",
        "position": "finance",
        "description": "rfdfersdfcresdfc",
        "email": "johnson@gmail.com",
        "linkedin": ""
    }
]